{
  "id": "project_details",
  "type": "SharedSlice",
  "name": "ProjectDetails",
  "description": "ProjectDetails",
  "variations": [
    {
      "id": "default",
      "name": "Default",
      "docURL": "...",
      "version": "initial",
      "description": "Default",
      "imageUrl": "",
      "primary": {
        "link": {
          "type": "Link",
          "config": {
            "label": "Link",
            "placeholder": "",
            "select": null
          }
        },
        "pinned": {
          "type": "Boolean",
          "config": {
            "label": "Pinned",
            "default_value": false,
            "placeholder_true": "true",
            "placeholder_false": "false"
          }
        }
      },
      "items": {
        "image": {
          "type": "Image",
          "config": {
            "label": "Image",
            "constraint": {},
            "thumbnails": []
          }
        }
      }
    }
  ]
}