{
  "id": "biography",
  "type": "SharedSlice",
  "name": "Biography",
  "description": "Biography",
  "variations": [
    {
      "id": "default",
      "name": "Default",
      "docURL": "...",
      "version": "initial",
      "description": "Default",
      "imageUrl": "",
      "primary": {
        "heading": {
          "type": "Text",
          "config": {
            "label": "Heading",
            "placeholder": ""
          }
        },
        "description": {
          "type": "StructuredText",
          "config": {
            "label": "Description",
            "placeholder": "",
            "allowTargetBlank": true,
            "single": "paragraph,preformatted,heading1,heading2,heading3,heading4,heading5,heading6,strong,em,hyperlink,image,embed,list-item,o-list-item,rtl"
          }
        },
        "button_text": {
          "type": "Text",
          "config": {
            "label": "Button text",
            "placeholder": ""
          }
        },
        "button_link": {
          "type": "Link",
          "config": {
            "label": "Button Link",
            "placeholder": "",
            "select": null
          }
        },
        "avatar": {
          "type": "Image",
          "config": {
            "label": "Avatar",
            "constraint": {},
            "thumbnails": []
          }
        },
        "phone_number_text": {
          "type": "Text",
          "config": {
            "label": "Phone number text",
            "placeholder": ""
          }
        },
        "phone_number": {
          "type": "Link",
          "config": {
            "label": "Phone number",
            "placeholder": "",
            "allowTargetBlank": false,
            "select": null
          }
        },
        "email_text": {
          "type": "Text",
          "config": {
            "label": "Email text",
            "placeholder": ""
          }
        },
        "email": {
          "type": "Link",
          "config": {
            "label": "Email",
            "placeholder": "",
            "allowTargetBlank": false,
            "select": null
          }
        }
      },
      "items": {}
    }
  ]
}